preservedfs/__init__.py
preservedfs/cli.py
preservedfs/preservedfs.py
preservedfs-0.1.5.dist-info/METADATA
preservedfs-0.1.5.dist-info/WHEEL
preservedfs-0.1.5.dist-info/entry_points.txt
preservedfs-0.1.5.dist-info/licenses/LICENSE
preservedfs-0.1.5.dist-info/RECORD
