Metadata-Version: 2.1
Name: preservedfs
Version: 0.1.5
Summary: A FileSystem that preserves original files.
Project-URL: Homepage, https://gitlab.com/KirmTwinty/preserved-fs
Project-URL: Bug Tracker, https://gitlab.com/KirmTwinty/preserved-fs/issues
Author-email: KirmTwinty <thibaud.toullier@inria.fr>
License:                     GNU GENERAL PUBLIC LICENSE
Classifier: License :: OSI Approved :: GNU General Public License v3 (GPLv3)
Classifier: Operating System :: OS Independent
Classifier: Programming Language :: Python :: 2
Classifier: Programming Language :: Python :: 3
Requires-Python: >=2.5
Requires-Dist: click
Requires-Dist: fuse-python
